verdict_sdk/__init__.py
verdict_sdk/client.py
verdict_sdk/exceptions.py
verdict_sdk/models.py
verdict_sdk-0.1.0.dist-info/METADATA
verdict_sdk-0.1.0.dist-info/WHEEL
verdict_sdk-0.1.0.dist-info/top_level.txt
verdict_sdk-0.1.0.dist-info/RECORD
